{
  "generated_at": "2026-07-19T04:02:47Z",
  "bar_close_utc": "2026-07-19T00:00:00Z",
  "timeframe": "1d",
  "strategy": "GaussianChannel v3.1",
  "asset_class": "crypto",
  "signals": [
    {
      "symbol": "BTC",
      "rank": 1,
      "state": "neutral",
      "hl_symbol": "BTC",
      "tradable_on_hl": true,
      "close": 64834.22,
      "gc_filter": 66698.36490109246,
      "gc_upper": 69847.57510664214,
      "gc_lower": 63549.15469554278
    },
    {
      "symbol": "ETH",
      "rank": 2,
      "state": "neutral",
      "hl_symbol": "ETH",
      "tradable_on_hl": true,
      "close": 1862.61,
      "gc_filter": 1823.9485531605835,
      "gc_upper": 1940.4089682342183,
      "gc_lower": 1707.4881380869488
    },
    {
      "symbol": "BNB",
      "rank": 4,
      "state": "neutral",
      "hl_symbol": "BNB",
      "tradable_on_hl": true,
      "close": 570.65,
      "gc_filter": 605.2954281112762,
      "gc_upper": 636.6281040352833,
      "gc_lower": 573.9627521872692
    },
    {
      "symbol": "XRP",
      "rank": 5,
      "state": "short",
      "hl_symbol": "XRP",
      "tradable_on_hl": true,
      "close": 1.0929,
      "gc_filter": 1.1967915069199386,
      "gc_upper": 1.2700943004141008,
      "gc_lower": 1.1234887134257765,
      "breakout_date": "2026-06-03"
    },
    {
      "symbol": "SOL",
      "rank": 7,
      "state": "neutral",
      "hl_symbol": "SOL",
      "tradable_on_hl": true,
      "close": 75.52,
      "gc_filter": 75.6139378058212,
      "gc_upper": 81.27633451713154,
      "gc_lower": 69.95154109451084
    },
    {
      "symbol": "TRX",
      "rank": 8,
      "state": "neutral",
      "hl_symbol": "TRX",
      "tradable_on_hl": true,
      "close": 0.3258,
      "gc_filter": 0.3312793039194498,
      "gc_upper": 0.33960068878970073,
      "gc_lower": 0.3229579190491989
    },
    {
      "symbol": "HYPE",
      "rank": 10,
      "state": "neutral",
      "hl_symbol": "HYPE",
      "tradable_on_hl": true,
      "close": 60.238,
      "gc_filter": 61.67400266877744,
      "gc_upper": 68.9682731632662,
      "gc_lower": 54.379732174288684
    },
    {
      "symbol": "DOGE",
      "rank": 11,
      "state": "short",
      "hl_symbol": "DOGE",
      "tradable_on_hl": true,
      "close": 0.07253,
      "gc_filter": 0.08767907890787377,
      "gc_upper": 0.09349739936804287,
      "gc_lower": 0.08186075844770467,
      "breakout_date": "2026-06-14"
    },
    {
      "symbol": "ZEC",
      "rank": 13,
      "state": "neutral",
      "hl_symbol": "ZEC",
      "tradable_on_hl": true,
      "close": 558.7,
      "gc_filter": 471.9097636705447,
      "gc_upper": 546.1160790922464,
      "gc_lower": 397.70344824884296
    },
    {
      "symbol": "LEO",
      "rank": 14,
      "state": "neutral",
      "hl_symbol": null,
      "tradable_on_hl": false,
      "close": 9.798,
      "gc_filter": 9.679821527180788,
      "gc_upper": 10.08412482299461,
      "gc_lower": 9.275518231366966
    },
    {
      "symbol": "ADA",
      "rank": 16,
      "state": "short",
      "hl_symbol": "ADA",
      "tradable_on_hl": true,
      "close": 0.1667,
      "gc_filter": 0.18915195324948136,
      "gc_upper": 0.20499520700502985,
      "gc_lower": 0.17330869949393288,
      "breakout_date": "2026-06-02"
    },
    {
      "symbol": "XLM",
      "rank": 17,
      "state": "neutral",
      "hl_symbol": "XLM",
      "tradable_on_hl": true,
      "close": 0.1879,
      "gc_filter": 0.19260414844414914,
      "gc_upper": 0.2166314233963909,
      "gc_lower": 0.16857687349190736
    },
    {
      "symbol": "XMR",
      "rank": 18,
      "state": "neutral",
      "hl_symbol": "XMR",
      "tradable_on_hl": true,
      "close": 335.5,
      "gc_filter": 342.60046402120196,
      "gc_upper": 377.5135784353589,
      "gc_lower": 307.687349607045
    },
    {
      "symbol": "LINK",
      "rank": 19,
      "state": "neutral",
      "hl_symbol": "LINK",
      "tradable_on_hl": true,
      "close": 8.35,
      "gc_filter": 8.280865982229809,
      "gc_upper": 8.85880798800693,
      "gc_lower": 7.702923976452688
    },
    {
      "symbol": "LAB",
      "rank": 20,
      "state": "neutral",
      "hl_symbol": null,
      "tradable_on_hl": false,
      "close": 0.1924,
      "gc_filter": 10.461217185165113,
      "gc_upper": 15.779417274442682,
      "gc_lower": 5.143017095887544
    },
    {
      "symbol": "WBT",
      "rank": 21,
      "state": "neutral",
      "hl_symbol": null,
      "tradable_on_hl": false,
      "close": 56.32,
      "gc_filter": 52.55982180002987,
      "gc_upper": 55.013549295319855,
      "gc_lower": 50.10609430473989
    },
    {
      "symbol": "CC",
      "rank": 22,
      "state": "short",
      "hl_symbol": "CC",
      "tradable_on_hl": true,
      "close": 0.12521,
      "gc_filter": 0.15338305456766455,
      "gc_upper": 0.1645293550767863,
      "gc_lower": 0.1422367540585428,
      "breakout_date": "2026-07-06"
    },
    {
      "symbol": "BCH",
      "rank": 23,
      "state": "short",
      "hl_symbol": "BCH",
      "tradable_on_hl": true,
      "close": 220.2,
      "gc_filter": 260.4397732028929,
      "gc_upper": 283.0485665038648,
      "gc_lower": 237.83097990192107,
      "breakout_date": "2026-05-15"
    },
    {
      "symbol": "TON",
      "rank": 24,
      "state": "short",
      "hl_symbol": "TON",
      "tradable_on_hl": true,
      "close": 1.474,
      "gc_filter": 1.7248052821774564,
      "gc_upper": 1.9349295398038129,
      "gc_lower": 1.5146810245511,
      "breakout_date": "2026-07-17"
    },
    {
      "symbol": "M",
      "rank": 28,
      "state": "short",
      "hl_symbol": null,
      "tradable_on_hl": false,
      "close": 1.2322,
      "gc_filter": 2.5644870859271056,
      "gc_upper": 3.0087288080550487,
      "gc_lower": 2.1202453637991625,
      "breakout_date": "2026-06-24"
    },
    {
      "symbol": "HBAR",
      "rank": 29,
      "state": "short",
      "hl_symbol": "HBAR",
      "tradable_on_hl": true,
      "close": 0.06711,
      "gc_filter": 0.08133161449153598,
      "gc_upper": 0.08684560756168472,
      "gc_lower": 0.07581762142138723,
      "breakout_date": "2026-06-07"
    },
    {
      "symbol": "LTC",
      "rank": 30,
      "state": "neutral",
      "hl_symbol": "LTC",
      "tradable_on_hl": true,
      "close": 47.01,
      "gc_filter": 46.69975580590818,
      "gc_upper": 49.38505060501194,
      "gc_lower": 44.014461006804424
    },
    {
      "symbol": "AVAX",
      "rank": 31,
      "state": "short",
      "hl_symbol": "AVAX",
      "tradable_on_hl": true,
      "close": 6.574,
      "gc_filter": 7.409631305126875,
      "gc_upper": 8.001748001908403,
      "gc_lower": 6.817514608345347,
      "breakout_date": "2026-06-04"
    },
    {
      "symbol": "NEAR",
      "rank": 32,
      "state": "neutral",
      "hl_symbol": "NEAR",
      "tradable_on_hl": true,
      "close": 1.932,
      "gc_filter": 2.0346044855985252,
      "gc_upper": 2.3210801696985497,
      "gc_lower": 1.748128801498501
    },
    {
      "symbol": "SUI",
      "rank": 33,
      "state": "neutral",
      "hl_symbol": "SUI",
      "tradable_on_hl": true,
      "close": 0.7434,
      "gc_filter": 0.8137277737750651,
      "gc_upper": 0.8877249733660896,
      "gc_lower": 0.7397305741840406
    },
    {
      "symbol": "SHIB",
      "rank": 34,
      "state": "short",
      "hl_symbol": "kSHIB",
      "tradable_on_hl": true,
      "close": 4.15e-06,
      "gc_filter": 4.965957439672267e-06,
      "gc_upper": 5.290500343314067e-06,
      "gc_lower": 4.641414536030467e-06,
      "breakout_date": "2026-06-04"
    },
    {
      "symbol": "CRO",
      "rank": 37,
      "state": "neutral",
      "hl_symbol": null,
      "tradable_on_hl": false,
      "close": 0.05945,
      "gc_filter": 0.061649426830510404,
      "gc_upper": 0.06496574452973221,
      "gc_lower": 0.058333109131288606
    },
    {
      "symbol": "XAUT",
      "rank": 38,
      "state": "short",
      "hl_symbol": null,
      "tradable_on_hl": false,
      "close": 4012.07,
      "gc_filter": 4275.776159293548,
      "gc_upper": 4389.220924316155,
      "gc_lower": 4162.33139427094,
      "breakout_date": "2026-06-25"
    },
    {
      "symbol": "TAO",
      "rank": 41,
      "state": "short",
      "hl_symbol": "TAO",
      "tradable_on_hl": true,
      "close": 196.1,
      "gc_filter": 236.6689978167444,
      "gc_upper": 261.67784880107064,
      "gc_lower": 211.66014683241815,
      "breakout_date": "2026-06-25"
    },
    {
      "symbol": "PAXG",
      "rank": 43,
      "state": "short",
      "hl_symbol": "PAXG",
      "tradable_on_hl": true,
      "close": 4012.29,
      "gc_filter": 4297.094500760544,
      "gc_upper": 4414.913170680313,
      "gc_lower": 4179.275830840776,
      "breakout_date": "2026-05-19"
    },
    {
      "symbol": "MNT",
      "rank": 44,
      "state": "short",
      "hl_symbol": "MNT",
      "tradable_on_hl": true,
      "close": 0.42,
      "gc_filter": 0.5478930956102483,
      "gc_upper": 0.5828834687729157,
      "gc_lower": 0.512902722447581,
      "breakout_date": "2026-06-03"
    },
    {
      "symbol": "WLFI",
      "rank": 45,
      "state": "neutral",
      "hl_symbol": "WLFI",
      "tradable_on_hl": true,
      "close": 0.0569,
      "gc_filter": 0.06034096501326933,
      "gc_upper": 0.0654824197517269,
      "gc_lower": 0.05519951027481176
    },
    {
      "symbol": "DOT",
      "rank": 46,
      "state": "short",
      "hl_symbol": "DOT",
      "tradable_on_hl": true,
      "close": 0.839,
      "gc_filter": 1.0220880653733837,
      "gc_upper": 1.1041325355972618,
      "gc_lower": 0.9400435951495056,
      "breakout_date": "2026-05-29"
    },
    {
      "symbol": "OKB",
      "rank": 48,
      "state": "neutral",
      "hl_symbol": null,
      "tradable_on_hl": false,
      "close": 81.37,
      "gc_filter": 78.99392736205739,
      "gc_upper": 84.49678120575864,
      "gc_lower": 73.49107351835615
    },
    {
      "symbol": "UNI",
      "rank": 49,
      "state": "neutral",
      "hl_symbol": "UNI",
      "tradable_on_hl": true,
      "close": 3.569,
      "gc_filter": 3.019640536749315,
      "gc_upper": 3.3187839988426107,
      "gc_lower": 2.7204970746560195
    },
    {
      "symbol": "ONDO",
      "rank": 50,
      "state": "neutral",
      "hl_symbol": "ONDO",
      "tradable_on_hl": true,
      "close": 0.347,
      "gc_filter": 0.34907618772898014,
      "gc_upper": 0.3914006663428694,
      "gc_lower": 0.30675170911509086
    },
    {
      "symbol": "ASTER",
      "rank": 51,
      "state": "neutral",
      "hl_symbol": "ASTER",
      "tradable_on_hl": true,
      "close": 0.62,
      "gc_filter": 0.6509925137641009,
      "gc_upper": 0.7007018315744651,
      "gc_lower": 0.6012831959537368
    },
    {
      "symbol": "ICP",
      "rank": 53,
      "state": "neutral",
      "hl_symbol": "ICP",
      "tradable_on_hl": true,
      "close": 2.175,
      "gc_filter": 2.42742277940484,
      "gc_upper": 2.692380196345539,
      "gc_lower": 2.1624653624641414
    },
    {
      "symbol": "HTX",
      "rank": 54,
      "state": "neutral",
      "hl_symbol": null,
      "tradable_on_hl": false,
      "close": 1.8247e-06,
      "gc_filter": 1.7748858687811693e-06,
      "gc_upper": 1.8328477350985841e-06,
      "gc_lower": 1.7169240024637544e-06
    },
    {
      "symbol": "SKY",
      "rank": 55,
      "state": "neutral",
      "hl_symbol": "SKY",
      "tradable_on_hl": true,
      "close": 0.06224,
      "gc_filter": 0.06113982820174435,
      "gc_upper": 0.06538325955983643,
      "gc_lower": 0.05689639684365228
    },
    {
      "symbol": "PI",
      "rank": 56,
      "state": "short",
      "hl_symbol": null,
      "tradable_on_hl": false,
      "close": 0.08548,
      "gc_filter": 0.13533636309767705,
      "gc_upper": 0.14454791884097237,
      "gc_lower": 0.12612480735438172,
      "breakout_date": "2026-05-16"
    },
    {
      "symbol": "BGB",
      "rank": 58,
      "state": "short",
      "hl_symbol": null,
      "tradable_on_hl": false,
      "close": 1.649,
      "gc_filter": 1.828018078218211,
      "gc_upper": 1.8946755203500603,
      "gc_lower": 1.7613606360863616,
      "breakout_date": "2026-06-11"
    },
    {
      "symbol": "WLD",
      "rank": 59,
      "state": "neutral",
      "hl_symbol": "WLD",
      "tradable_on_hl": true,
      "close": 0.3762,
      "gc_filter": 0.4442531390689023,
      "gc_upper": 0.5303006486272219,
      "gc_lower": 0.35820562951058266
    },
    {
      "symbol": "PEPE",
      "rank": 60,
      "state": "neutral",
      "hl_symbol": "kPEPE",
      "tradable_on_hl": true,
      "close": 2.75e-06,
      "gc_filter": 3.004077615014116e-06,
      "gc_upper": 3.2636682324036965e-06,
      "gc_lower": 2.744486997624536e-06
    },
    {
      "symbol": "MORPHO",
      "rank": 62,
      "state": "neutral",
      "hl_symbol": "MORPHO",
      "tradable_on_hl": true,
      "close": 2.011,
      "gc_filter": 1.9243220218097568,
      "gc_upper": 2.1337476452330457,
      "gc_lower": 1.7148963983864678
    },
    {
      "symbol": "ETC",
      "rank": 63,
      "state": "short",
      "hl_symbol": "ETC",
      "tradable_on_hl": true,
      "close": 7.01,
      "gc_filter": 7.619867896333273,
      "gc_upper": 8.146108663251113,
      "gc_lower": 7.093627129415432,
      "breakout_date": "2026-06-13"
    },
    {
      "symbol": "H",
      "rank": 64,
      "state": "short",
      "hl_symbol": null,
      "tradable_on_hl": false,
      "close": 0.05851,
      "gc_filter": 0.23987606004924855,
      "gc_upper": 0.37394340134927817,
      "gc_lower": 0.1058087187492189,
      "breakout_date": "2026-07-16"
    },
    {
      "symbol": "AAVE",
      "rank": 65,
      "state": "long",
      "hl_symbol": "AAVE",
      "tradable_on_hl": true,
      "close": 89.99,
      "gc_filter": 80.59403647277077,
      "gc_upper": 88.40854372440582,
      "gc_lower": 72.77952922113572,
      "breakout_date": "2026-07-17"
    },
    {
      "symbol": "RENDER",
      "rank": 66,
      "state": "short",
      "hl_symbol": "RENDER",
      "tradable_on_hl": true,
      "close": 1.482,
      "gc_filter": 1.7446586796389902,
      "gc_upper": 1.930800231662532,
      "gc_lower": 1.5585171276154486,
      "breakout_date": "2026-06-25"
    },
    {
      "symbol": "QNT",
      "rank": 67,
      "state": "neutral",
      "hl_symbol": null,
      "tradable_on_hl": false,
      "close": 63.86,
      "gc_filter": 69.98007725056488,
      "gc_upper": 75.43037033827363,
      "gc_lower": 64.52978416285612
    },
    {
      "symbol": "ALGO",
      "rank": 69,
      "state": "short",
      "hl_symbol": "ALGO",
      "tradable_on_hl": true,
      "close": 0.0833,
      "gc_filter": 0.09839920231102933,
      "gc_upper": 0.10769263178237345,
      "gc_lower": 0.08910577283968521,
      "breakout_date": "2026-06-13"
    },
    {
      "symbol": "KCS",
      "rank": 70,
      "state": "short",
      "hl_symbol": null,
      "tradable_on_hl": false,
      "close": 6.647,
      "gc_filter": 7.273033841710201,
      "gc_upper": 7.738237429909666,
      "gc_lower": 6.807830253510736,
      "breakout_date": "2026-07-17"
    },
    {
      "symbol": "POL",
      "rank": 72,
      "state": "neutral",
      "hl_symbol": "POL",
      "tradable_on_hl": true,
      "close": 0.08103,
      "gc_filter": 0.08128451109916501,
      "gc_upper": 0.08698162320919696,
      "gc_lower": 0.07558739898913307
    },
    {
      "symbol": "ATOM",
      "rank": 75,
      "state": "short",
      "hl_symbol": "ATOM",
      "tradable_on_hl": true,
      "close": 1.498,
      "gc_filter": 1.8160019238618985,
      "gc_upper": 1.9559274820768862,
      "gc_lower": 1.6760763656469109,
      "breakout_date": "2026-06-23"
    },
    {
      "symbol": "VVV",
      "rank": 78,
      "state": "short",
      "hl_symbol": "VVV",
      "tradable_on_hl": true,
      "close": 11.8251,
      "gc_filter": 14.683453454637906,
      "gc_upper": 17.322271431095942,
      "gc_lower": 12.044635478179872,
      "breakout_date": "2026-07-08"
    },
    {
      "symbol": "DEXE",
      "rank": 79,
      "state": "long",
      "hl_symbol": null,
      "tradable_on_hl": false,
      "close": 35.357,
      "gc_filter": 19.00567896235945,
      "gc_upper": 22.690724013567237,
      "gc_lower": 15.320633911151663,
      "breakout_date": "2026-06-24"
    },
    {
      "symbol": "JST",
      "rank": 81,
      "state": "long",
      "hl_symbol": null,
      "tradable_on_hl": false,
      "close": 0.09855,
      "gc_filter": 0.08517043812110789,
      "gc_upper": 0.09083226712060004,
      "gc_lower": 0.07950860912161574,
      "breakout_date": "2026-07-10"
    },
    {
      "symbol": "NEXO",
      "rank": 82,
      "state": "neutral",
      "hl_symbol": null,
      "tradable_on_hl": false,
      "close": 0.76,
      "gc_filter": 0.8024454781145316,
      "gc_upper": 0.8516163680751402,
      "gc_lower": 0.753274588153923
    },
    {
      "symbol": "KAS",
      "rank": 83,
      "state": "short",
      "hl_symbol": "KAS",
      "tradable_on_hl": true,
      "close": 0.02777,
      "gc_filter": 0.031239113944731365,
      "gc_upper": 0.03381253193978201,
      "gc_lower": 0.028665695949680717,
      "breakout_date": "2026-07-16"
    },
    {
      "symbol": "ENA",
      "rank": 84,
      "state": "neutral",
      "hl_symbol": "ENA",
      "tradable_on_hl": true,
      "close": 0.0806,
      "gc_filter": 0.08962982614892107,
      "gc_upper": 0.10159958577428065,
      "gc_lower": 0.07766006652356149
    },
    {
      "symbol": "GT",
      "rank": 85,
      "state": "neutral",
      "hl_symbol": null,
      "tradable_on_hl": false,
      "close": 6.75,
      "gc_filter": 6.747282623585916,
      "gc_upper": 7.084811388626968,
      "gc_lower": 6.409753858544863
    },
    {
      "symbol": "FIL",
      "rank": 86,
      "state": "neutral",
      "hl_symbol": "FIL",
      "tradable_on_hl": true,
      "close": 0.749,
      "gc_filter": 0.8361799696338054,
      "gc_upper": 0.9233462961328125,
      "gc_lower": 0.7490136431347982
    },
    {
      "symbol": "APT",
      "rank": 87,
      "state": "short",
      "hl_symbol": "APT",
      "tradable_on_hl": true,
      "close": 0.608,
      "gc_filter": 0.7406393016669361,
      "gc_upper": 0.8119498880313472,
      "gc_lower": 0.6693287153025251,
      "breakout_date": "2026-06-07"
    },
    {
      "symbol": "INJ",
      "rank": 88,
      "state": "neutral",
      "hl_symbol": "INJ",
      "tradable_on_hl": true,
      "close": 5.166,
      "gc_filter": 5.069853763063779,
      "gc_upper": 5.758792491339862,
      "gc_lower": 4.380915034787697
    },
    {
      "symbol": "JUP",
      "rank": 89,
      "state": "neutral",
      "hl_symbol": "JUP",
      "tradable_on_hl": true,
      "close": 0.1948,
      "gc_filter": 0.19836419675325218,
      "gc_upper": 0.22305755231317737,
      "gc_lower": 0.17367084119332699
    },
    {
      "symbol": "XDC",
      "rank": 90,
      "state": "short",
      "hl_symbol": null,
      "tradable_on_hl": false,
      "close": 0.02806,
      "gc_filter": 0.03009848537433699,
      "gc_upper": 0.03192418096845215,
      "gc_lower": 0.028272789780221828,
      "breakout_date": "2026-07-05"
    },
    {
      "symbol": "NIGHT",
      "rank": 91,
      "state": "short",
      "hl_symbol": null,
      "tradable_on_hl": false,
      "close": 0.02767,
      "gc_filter": 0.03288486715748849,
      "gc_upper": 0.03646824086452183,
      "gc_lower": 0.029301493450455154,
      "breakout_date": "2026-07-17"
    },
    {
      "symbol": "FLR",
      "rank": 92,
      "state": "short",
      "hl_symbol": null,
      "tradable_on_hl": false,
      "close": 0.006567,
      "gc_filter": 0.007430541757205107,
      "gc_upper": 0.007876773599684904,
      "gc_lower": 0.00698430991472531,
      "breakout_date": "2026-06-17"
    },
    {
      "symbol": "BDX",
      "rank": 94,
      "state": "short",
      "hl_symbol": null,
      "tradable_on_hl": false,
      "close": 0.12,
      "gc_filter": 0.34364896624107033,
      "gc_upper": 0.41850203870044955,
      "gc_lower": 0.2687958937816911,
      "breakout_date": "2026-07-13"
    },
    {
      "symbol": "PUMP",
      "rank": 95,
      "state": "neutral",
      "hl_symbol": "PUMP",
      "tradable_on_hl": true,
      "close": 0.001663,
      "gc_filter": 0.001578227003773802,
      "gc_upper": 0.001781988533412917,
      "gc_lower": 0.001374465474134687
    },
    {
      "symbol": "FET",
      "rank": 96,
      "state": "short",
      "hl_symbol": "FET",
      "tradable_on_hl": true,
      "close": 0.1586,
      "gc_filter": 0.20076161584033617,
      "gc_upper": 0.22511067118541084,
      "gc_lower": 0.1764125604952615,
      "breakout_date": "2026-07-04"
    },
    {
      "symbol": "ARB",
      "rank": 97,
      "state": "neutral",
      "hl_symbol": "ARB",
      "tradable_on_hl": true,
      "close": 0.0884,
      "gc_filter": 0.09133794639767333,
      "gc_upper": 0.09980152658160114,
      "gc_lower": 0.08287436621374551
    }
  ]
}
